Metadata-Version: 2.1
Name: aissistant
Version: 0.7
Summary: Aissistant v0.7
Home-page: https://github.com/markomanninen/aissistant
Author: Marko Manninen
License: MIT
Classifier: Development Status :: 3 - Alpha
Classifier: Intended Audience :: Developers
Classifier: License :: OSI Approved :: MIT License
Classifier: Programming Language :: Python :: 3
Classifier: Programming Language :: Python :: 3.6
Classifier: Programming Language :: Python :: 3.7
Classifier: Programming Language :: Python :: 3.8
Classifier: Programming Language :: Python :: 3.9
Provides-Extra: gpu
Provides-Extra: cpu
License-File: LICENSE
